README.md
setup.cfg
setup.py
data_distributions/Binomialdistribution.py
data_distributions/Gaussiandistribution.py
data_distributions/Generaldistribution.py
data_distributions/__init__.py
data_distributions.egg-info/PKG-INFO
data_distributions.egg-info/SOURCES.txt
data_distributions.egg-info/dependency_links.txt
data_distributions.egg-info/not-zip-safe
data_distributions.egg-info/top_level.txt